verify/__init__.py
verify/base64salt_util.py
verify/verify_valid.py
verify_valid-0.0.2.dist-info/LICENSE
verify_valid-0.0.2.dist-info/METADATA
verify_valid-0.0.2.dist-info/WHEEL
verify_valid-0.0.2.dist-info/top_level.txt
verify_valid-0.0.2.dist-info/RECORD
